LICENSE
NOTICE
README.md
setup.py
mavenpy/__init__.py
mavenpy/run.py
mavenpy/settings.py
mavenpy.egg-info/PKG-INFO
mavenpy.egg-info/SOURCES.txt
mavenpy.egg-info/dependency_links.txt
mavenpy.egg-info/requires.txt
mavenpy.egg-info/top_level.txt